founders/__init__.py
founders/server.py
founders/status.py
founders/user.py
founders-0.1.1.dist-info/LICENSE
founders-0.1.1.dist-info/METADATA
founders-0.1.1.dist-info/WHEEL
founders-0.1.1.dist-info/top_level.txt
founders-0.1.1.dist-info/RECORD
