Metadata-Version: 2.1
Name: founders
Version: 0.1.1
Summary: A small package for the founders api
Home-page: https://github.com/shupik123/FoundersApiPy
Author: shupik
License: UNKNOWN
Platform: UNKNOWN
Classifier: Programming Language :: Python :: 3
Classifier: Operating System :: OS Independent
Requires-Python: >=3.6
Requires-Dist: requests
